prv_accountant/__init__.py
prv_accountant/accountant.py
prv_accountant/composers.py
prv_accountant/discrete_privacy_random_variable.py
prv_accountant/discretisers.py
prv_accountant/domain.py
prv_accountant/dpsgd.py
prv_accountant/other_accountants.py
prv_accountant/privacy_random_variables/__init__.py
prv_accountant/privacy_random_variables/abstract_privacy_random_variable.py
prv_accountant/privacy_random_variables/approximate_dp.py
prv_accountant/privacy_random_variables/gaussian_mechanism.py
prv_accountant/privacy_random_variables/laplace_mechanism.py
prv_accountant/privacy_random_variables/poisson_subsampled_gaussian_mechanism.py
prv_accountant/privacy_random_variables/pure_dp_mechanism.py
prv_accountant-0.2.0.data/scripts/compute-dp-epsilon
prv_accountant-0.2.0.dist-info/LICENSE
prv_accountant-0.2.0.dist-info/METADATA
prv_accountant-0.2.0.dist-info/WHEEL
prv_accountant-0.2.0.dist-info/top_level.txt
prv_accountant-0.2.0.dist-info/RECORD
