Metadata-Version: 2.1
Name: prv-accountant
Version: 0.2.0
Summary: A fast algorithm to optimally compose privacy guarantees of differentially private (DP) mechanisms to arbitrary accuracy.
Home-page: https://github.com/microsoft/prv_accountant
Author: Microsoft Corporation
Requires-Python: >=3.7.0
License-File: LICENSE
Requires-Dist: numpy
Requires-Dist: scipy
Provides-Extra: extra
Requires-Dist: plotly ; extra == 'extra'
Requires-Dist: tqdm ; extra == 'extra'
Requires-Dist: jupyter ; extra == 'extra'
Requires-Dist: sympy ; extra == 'extra'
Requires-Dist: tensorflow-privacy ; extra == 'extra'
Requires-Dist: nbconvert ; extra == 'extra'
Requires-Dist: pandas ; extra == 'extra'
Requires-Dist: pytest ; extra == 'extra'
Requires-Dist: flake8 ; extra == 'extra'
